[null,
    {"value" : "<?php", "name" : "BodyString"},
    [
        {"value" : "echo", "name" : "'echo'"},
        {"value" : "\"hello \"", "name" : "DoubleQuotedString"},
        {"value" : "\"world\"", "name" : "DoubleQuotedString"}
    ],
    [
        {"value" : "global", "name" : "'global'"},
        ["$", "a"],
        ["$", "b"]
    ],
    {"value" : "break", "name" : "'break'"},
    [
        {"value" : "break", "name" : "'break'"},
        {"value" : "20", "name" : "Integer"}
    ],
    {"value" : "continue", "name" : "'continue'"},
    [
        {"value" : "continue", "name" : "'continue'"},
        {"value" : "10", "name" : "Integer"}
    ],
    [
        {"value" : "return", "name" : "'return'"},
        ["$", "a"]
    ],
    [
        {"value" : "require", "name" : "RequireOperator"},
        {"value" : "'test.php'", "name" : "SingleQuotedString"}
    ],
    [
        {"value" : "static", "name" : "'static'"},
        ["$", "a"], 
        {"value" : "5", "name" : "Integer"}
    ],
    {"value" : "?>", "name" : "BodyString"}
]